pypedrive
