Metadata-Version: 1.1
Name: pypedrive
Version: 0.1.3
Summary: Light API for pipedrive.com
Home-page: http://github.com/orige/pypedrive
Author: Eduardo Orige
Author-email: eduardo.orige@gmail.com
License: MIT
Download-URL: http://github.com/orige/pypedrive/downloads
Keywords: light pipedrive api
Platform: UNKNOWN
